onepassword.py
onepassword-0.4.1.dist-info/LICENSE
onepassword-0.4.1.dist-info/WHEEL
onepassword-0.4.1.dist-info/METADATA
onepassword-0.4.1.dist-info/RECORD
